libal/__init__.py
libal/libal.so
libal/camera/__init__.py
libal/net/__init__.py
aluminium_library-0.2.dist-info/LICENSE.txt
aluminium_library-0.2.dist-info/METADATA
aluminium_library-0.2.dist-info/WHEEL
aluminium_library-0.2.dist-info/top_level.txt
aluminium_library-0.2.dist-info/RECORD
